[
  {
    "title": "How I use Odoo for Small Business Accounting",
    "description": "A deep dive into leveraging Odoo's accounting module for efficient financial management in small businesses.",
    "url": "blog/odoo.html"
  },
  {
    "title": "Tips for Learning Business English Effectively",
    "description": "My personal journey and effective strategies for mastering Business English for a career in finance.",
    "url": "blog/english.html"
  },
  {
    "title": "New Article Title",
    "description": "Add a short description for your new article here.",
    "url": "blog/new-article-link.html"
  }
]
